pathwayenrichment/__init__.py
pathwayenrichment/clusteranalysis.py
pathwayenrichment/databaseparser.py
pathwayenrichment/representation.py
pathwayenrichment/utils.py
pathwayenrichment/visualization.py
pathwayenrichment-0.0.3.dist-info/LICENSE
pathwayenrichment-0.0.3.dist-info/METADATA
pathwayenrichment-0.0.3.dist-info/WHEEL
pathwayenrichment-0.0.3.dist-info/top_level.txt
pathwayenrichment-0.0.3.dist-info/RECORD
