Metadata-Version: 2.1
Name: pathwayenrichment
Version: 0.0.3
Summary: Perform permutation-based pathway enrichment analysis
Home-page: http://github.com/robaina/pathwayEnrichment
Author: Semidán Robaina Estévez
Author-email: srobaina@ull.edu.es
Maintainer: Semidán Robaina Estévez
Maintainer-email: srobaina@gmail.com
License: Creative Commons Attribution 4.0 International
Download-URL: http://github.com/robaina/pathwayEnrichment
Platform: UNKNOWN
License-File: LICENSE
Requires-Dist: numpy
Requires-Dist: pandas
Requires-Dist: matplotlib
Requires-Dist: requests
Requires-Dist: scikit-learn
